skp4/__init__.py
skp4/binary.py
skp4/calculation.py
skp4/classification_type.py
skp4/confusion.py
skp4/dataset.py
skp4/exceptions.py
skp4/formulas/__init__.py
skp4/formulas/f1.py
skp4/formulas/npv.py
skp4/formulas/p4.py
skp4/formulas/precision.py
skp4/formulas/recall.py
skp4/formulas/specificity.py
skp4/generators/binary_generators.py
skp4/generators/multilabel_generators.py
skp4/interface.py
skp4/metrics.py
skp4/multilabel.py
skp4/result.py
skp4/score.py
scikit_p4-0.1.1.dist-info/LICENSE
scikit_p4-0.1.1.dist-info/METADATA
scikit_p4-0.1.1.dist-info/WHEEL
scikit_p4-0.1.1.dist-info/RECORD
