Metadata-Version: 2.3
Name: scikit-p4
Version: 0.1.1
Summary: P4 metric calculation library compatible with scikit-learn
License: BSD-3-Clause
Keywords: metrics,classification,p4,scikit-learn
Author: Mikolaj Sitarz
Author-email: sitarz@refaba.com
Requires-Python: >=3.11
Classifier: License :: OSI Approved :: BSD License
Classifier: Operating System :: OS Independent
Classifier: Programming Language :: Python :: 3
Classifier: Programming Language :: Python :: 3.11
Classifier: Programming Language :: Python :: 3.12
Classifier: Programming Language :: Python :: 3.13
Requires-Dist: numpy
Requires-Dist: scikit-learn (>=1.7.1,<2.0)
Project-URL: Homepage, https://github.com/mikolaj1024/scikit-p4
Project-URL: Repository, https://github.com/mikolaj1024/scikit-p4
